<?xml version="1.0" encoding="utf-8" ?>
<dwsync>
<file name="add.php" server="107.161.187.74/rsa_live/" local="130604221800000000" remote="130604221800000000" />
<file name="addI.php" server="107.161.187.74/rsa_live/" local="130604499682492369" remote="130604542200000000" />
<file name="addITEST2.php" server="107.161.187.74/rsa_live/" local="130604221800000000" remote="130604221800000000" />
<file name="addP.php" server="107.161.187.74/rsa_live/" local="130604498873694799" remote="130604535600000000" />
<file name="addPTEST.php" server="107.161.187.74/rsa_live/" local="130604221800000000" remote="130604221800000000" />
<file name="addPTEST2.php" server="107.161.187.74/rsa_live/" local="130604221800000000" remote="130604221800000000" />
<file name="address.php" server="107.161.187.74/rsa_live/" local="130604221800000000" remote="130604221800000000" />
<file name="adminBarUI.php" server="107.161.187.74/rsa_live/" local="130604221800000000" remote="130604221800000000" />
<file name="arrayTEST.php" server="107.161.187.74/rsa_live/" local="130604221800000000" remote="130604221800000000" />
<file name="docctr.php" server="107.161.187.74/rsa_live/" local="130604506125780834" remote="130604542200000000" />
<file name="droppablePics.php" server="107.161.187.74/rsa_live/" local="130604221800000000" remote="130604221800000000" />
<file name="droppableTest.php" server="107.161.187.74/rsa_live/" local="130604221800000000" remote="130604221800000000" />
<file name="error_log" server="107.161.187.74/rsa_live/" local="130604233800000000" remote="130604233800000000" />
<file name="inventory.php" server="107.161.187.74/rsa_live/" local="130604221800000000" remote="130604221800000000" />
<file name="login.php" server="107.161.187.74/rsa_live/" local="130604221800000000" remote="130604221800000000" />
<file name="logout.php" server="107.161.187.74/rsa_live/" local="130604508715183473" remote="130604544600000000" />
<file name="members.php" server="107.161.187.74/rsa_live/" local="130604221800000000" remote="130604221800000000" />
<file name="membersT.php" server="107.161.187.74/rsa_live/" local="130604221800000000" remote="130604221800000000" />
<file name="membersTemplate.php" server="107.161.187.74/rsa_live/" local="130604221800000000" remote="130604221800000000" />
<file name="mylogin.php" server="107.161.187.74/rsa_live/" local="130604506627448678" remote="130604542200000000" />
<file name="mylogin2.php" server="107.161.187.74/rsa_live/" local="130604221800000000" remote="130604221800000000" />
<file name="myproductPics.php" server="107.161.187.74/rsa_live/" local="130604221800000000" remote="130604221800000000" />
<file name="myproducts.php" server="107.161.187.74/rsa_live/" local="130604502258980077" remote="130604542200000000" />
<file name="myproductsT.php" server="107.161.187.74/rsa_live/" local="130604221800000000" remote="130604221800000000" />
<file name="myproductsTEST.php" server="107.161.187.74/rsa_live/" local="130604222400000000" remote="130604222400000000" />
<file name="myPTEST2.php" server="107.161.187.74/rsa_live/" local="130604222400000000" remote="130604222400000000" />
<file name="overview.php" server="107.161.187.74/rsa_live/" local="130604493306692738" remote="130606476600000000" />
<file name="overviewA.php" server="107.161.187.74/rsa_live/" local="130604222400000000" remote="130604222400000000" />
<file name="pictures.php" server="107.161.187.74/rsa_live/" local="130604222400000000" remote="130604222400000000" />
<file name="pictures2.php" server="107.161.187.74/rsa_live/" local="130604222400000000" remote="130604222400000000" />
<file name="pictures3.php" server="107.161.187.74/rsa_live/" local="130604222400000000" remote="130604222400000000" />
<file name="pictures4.php" server="107.161.187.74/rsa_live/" local="130604222400000000" remote="130604222400000000" />
<file name="pictures5.php" server="107.161.187.74/rsa_live/" local="130604222400000000" remote="130604222400000000" />
<file name="processFirstPicture.php" server="107.161.187.74/rsa_live/" local="130604222400000000" remote="130604222400000000" />
<file name="register.php" server="107.161.187.74/rsa_live/" local="130604222400000000" remote="130604222400000000" />
<file name="reviewDocs.php" server="107.161.187.74/rsa_live/" local="130604505766432763" remote="130604541600000000" />
<file name="sLOGO4c.jpg" server="107.161.187.74/rsa_live/" local="130604222400000000" remote="130604222400000000" />
<file name="sLOGO4MYdocsSUMMARY.jpg" server="107.161.187.74/rsa_live/" local="130604222400000000" remote="130604222400000000" />
<file name="sLOGO4MYPRODUCTSUMMARY.jpg" server="107.161.187.74/rsa_live/" local="130604222400000000" remote="130604222400000000" />
<file name="sLOGO4QuickLogin.jpg" server="107.161.187.74/rsa_live/" local="130604222400000000" remote="130604222400000000" />
<file name="testDate.php" server="107.161.187.74/rsa_live/" local="130604222400000000" remote="130604222400000000" />
<file name="TESTEDIT.php" server="107.161.187.74/rsa_live/" local="130604222400000000" remote="130604222400000000" />
<file name="updateProfile.php" server="107.161.187.74/rsa_live/" local="130604506478506299" remote="130604542200000000" />
<file name="viewfrontlistings.php" server="107.161.187.74/rsa_live/" local="130604222400000000" remote="130604222400000000" />
<file name="viewlistings.php" server="107.161.187.74/rsa_live/" local="130604222400000000" remote="130604222400000000" />
<file name="viewrequests.php" server="107.161.187.74/rsa_live/" local="130604222400000000" remote="130604222400000000" />
<file name="viewuser.php" server="107.161.187.74/rsa_live/" local="130604222400000000" remote="130604222400000000" />
</dwsync>