<?xml version="1.0" encoding="utf-8" ?>
<dwsync>
<file name="buy.php" server="107.161.187.74/rsa_live/" local="130604379279331807" remote="130604415000000000" />
<file name="buyForm.php" server="107.161.187.74/rsa_live/" local="130604221800000000" remote="130604221800000000" />
<file name="error_log" server="107.161.187.74/rsa_live/" local="130604242200000000" remote="130604242200000000" />
<file name="login.php" server="107.161.187.74/rsa_live/" local="130604221800000000" remote="130604221800000000" />
<file name="OLDindex.html" server="107.161.187.74/rsa_live/" local="130604221800000000" remote="130604221800000000" />
<file name="pDetails1MockupLightB.php" server="107.161.187.74/rsa_live/" local="130604221800000000" remote="130604221800000000" />
<file name="register.php" server="107.161.187.74/rsa_live/" local="130604221800000000" remote="130604221800000000" />
<file name="registration.html" server="107.161.187.74/rsa_live/" local="130604221800000000" remote="130604221800000000" />
<file name="registration.php" server="107.161.187.74/rsa_live/" local="130606132931085952" remote="130606476600000000" />
<file name="titleBarF.php" server="107.161.187.74/rsa_live/" local="130604221800000000" remote="130604498400000000" />
<file name="index.php" server="107.161.187.74/rsa_live/" local="130606168698398790" remote="130606204800000000" />
</dwsync>